src/__init__.py
src/simulate.py
TimeSeriesSimulator-0.0.3.dist-info/LICENSE
TimeSeriesSimulator-0.0.3.dist-info/METADATA
TimeSeriesSimulator-0.0.3.dist-info/WHEEL
TimeSeriesSimulator-0.0.3.dist-info/top_level.txt
TimeSeriesSimulator-0.0.3.dist-info/RECORD
